gekitchensdk/__init__.py
gekitchensdk/ge_appliance.py
gekitchensdk/clients/__init__.py
gekitchensdk/clients/async_helpers.py
gekitchensdk/clients/async_login_flows.py
gekitchensdk/clients/base_client.py
gekitchensdk/clients/const.py
gekitchensdk/clients/ge_client_xmpp.py
gekitchensdk/clients/states.py
gekitchensdk/clients/websocket_client.py
gekitchensdk/clients/xmpp_client.py
gekitchensdk/erd/__init__.py
gekitchensdk/erd/erd_code_class.py
gekitchensdk/erd/erd_codes.py
gekitchensdk/erd/erd_configuration.py
gekitchensdk/erd/erd_encoder.py
gekitchensdk/erd/converters/__init__.py
gekitchensdk/erd/converters/abstract.py
gekitchensdk/erd/converters/dishwasher/__init__.py
gekitchensdk/erd/converters/dishwasher/cycle_name_converter.py
gekitchensdk/erd/converters/dishwasher/erd_cycle_state_converter.py
gekitchensdk/erd/converters/dishwasher/erd_rinse_agent_converter.py
gekitchensdk/erd/converters/dishwasher/operating_mode_converter.py
gekitchensdk/erd/converters/fridge/__init__.py
gekitchensdk/erd/converters/fridge/erd_filter_status_converter.py
gekitchensdk/erd/converters/fridge/fridge_door_status_converter.py
gekitchensdk/erd/converters/fridge/fridge_ice_bucket_status_converter.py
gekitchensdk/erd/converters/fridge/fridge_model_info_converter.py
gekitchensdk/erd/converters/fridge/fridge_set_point_limits_converter.py
gekitchensdk/erd/converters/fridge/fridge_set_points_converter.py
gekitchensdk/erd/converters/fridge/hot_water_status_converter.py
gekitchensdk/erd/converters/fridge/ice_maker_control_status_converter.py
gekitchensdk/erd/converters/laundry/__init__.py
gekitchensdk/erd/converters/laundry/dryness_level_converter.py
gekitchensdk/erd/converters/laundry/erd_time_remaining_converter.py
gekitchensdk/erd/converters/laundry/laundry_cycle_converter.py
gekitchensdk/erd/converters/laundry/laundry_door_status_converter.py
gekitchensdk/erd/converters/laundry/machine_state_converter.py
gekitchensdk/erd/converters/laundry/machine_subcycle_converter.py
gekitchensdk-0.3.11.dist-info/LICENSE
gekitchensdk-0.3.11.dist-info/METADATA
gekitchensdk-0.3.11.dist-info/WHEEL
gekitchensdk-0.3.11.dist-info/top_level.txt
gekitchensdk-0.3.11.dist-info/RECORD
