Metadata-Version: 2.1
Name: gekitchensdk
Version: 0.3.11
Summary: Python SDK for GE Kitchen Appliances
Home-page: https://github.com/simbaja/gekitchen
Author: Jack Simbach
Author-email: jack.simbach@gmail.com
License: MIT
Platform: UNKNOWN
Classifier: License :: OSI Approved :: MIT License
Classifier: Programming Language :: Python :: 3
Classifier: Programming Language :: Python :: 3.7
Requires-Dist: aiohttp
Requires-Dist: bidict
Requires-Dist: requests
Requires-Dist: websockets
Provides-Extra: xmpp
Requires-Dist: slixmpp (==1.5.2) ; extra == 'xmpp'
